deepagent_code/__init__.py
deepagent_code/cli.py
deepagent_code/utils.py
deepagent_code-0.1.4.dist-info/licenses/LICENSE
deepagent_code-0.1.4.dist-info/METADATA
deepagent_code-0.1.4.dist-info/WHEEL
deepagent_code-0.1.4.dist-info/entry_points.txt
deepagent_code-0.1.4.dist-info/top_level.txt
deepagent_code-0.1.4.dist-info/RECORD
