Metadata-Version: 2.4
Name: deepagent-code
Version: 0.1.4
Summary: A Claude Code-style CLI for running LangGraph agents from the terminal
Author-email: Kedar Dabhadkar <kdabhadk@gmail.com>
License-Expression: MIT
Project-URL: Homepage, https://github.com/dkedar7/deepagent-code
Project-URL: Repository, https://github.com/dkedar7/deepagent-code
Project-URL: Issues, https://github.com/dkedar7/deepagent-code/issues
Keywords: langgraph,cli,agents,llm,ai,claude-code
Classifier: Development Status :: 3 - Alpha
Classifier: Intended Audience :: Developers
Classifier: Programming Language :: Python :: 3
Classifier: Programming Language :: Python :: 3.11
Classifier: Programming Language :: Python :: 3.12
Classifier: Programming Language :: Python :: 3.13
Classifier: Programming Language :: Python :: 3.14
Requires-Python: >=3.11
License-File: LICENSE
Requires-Dist: langgraph>=0.2.0
Requires-Dist: click>=8.0.0
Requires-Dist: python-dotenv
Requires-Dist: deepagents
Provides-Extra: dev
Requires-Dist: pytest>=7.0.0; extra == "dev"
Requires-Dist: pytest-asyncio>=0.21.0; extra == "dev"
Requires-Dist: black>=23.0.0; extra == "dev"
Requires-Dist: ruff>=0.1.0; extra == "dev"
Requires-Dist: mypy>=1.0.0; extra == "dev"
Dynamic: license-file
